markdown_include_variants/__init__.py
markdown_include_variants/_main.py
markdown_include_variants/_version.py
markdown_include_variants/py.typed
markdown_include_variants-0.0.8.dist-info/METADATA
markdown_include_variants-0.0.8.dist-info/WHEEL
markdown_include_variants-0.0.8.dist-info/licenses/LICENSE
markdown_include_variants-0.0.8.dist-info/RECORD
