Metadata-Version: 2.4
Name: markdown-include-variants
Version: 0.0.8
Summary: Markdown extension to expand directives to include source example files to also include their variants. Only useful to tiangolo's projets. Don't use it. 😅
Project-URL: Homepage, https://github.com/tiangolo/markdown-include-variants
Project-URL: Repository, https://github.com/tiangolo/markdown-include-variants
Project-URL: Issues, https://github.com/tiangolo/markdown-include-variants/issues
Project-URL: Changelog, https://github.com/tiangolo/markdown-include-variants/release-notes.md
Author-email: Sebastián Ramírez <tiangolo@gmail.com>
License-File: LICENSE
Classifier: Intended Audience :: Developers
Classifier: License :: OSI Approved :: MIT License
Classifier: Typing :: Typed
Requires-Python: >=3.9
Requires-Dist: markdown>=3.7
